{
  "pxd": "PXD023867",
  "title": null,
  "summary": {
    "acquisition_type": "DDA",
    "quantification_method": "TMT reporter ion peak intensities",
    "labeling_strategy": [
      "TMT"
    ],
    "treatment_categories": [
      "genetic perturbation"
    ],
    "cell_types": [],
    "cell_lines": [
      "C8161.9"
    ],
    "sample_scope": "subproteome",
    "sample_scope_label": "phosphoproteome",
    "sample_scope_curie": "PPA:0000195",
    "instrument": null
  },
  "treatment": {
    "primary_variables": [
      {
        "ontology_label": "genetic perturbation",
        "ontology_curie": "PPA:0000011",
        "category": "genetic",
        "matched_parent_class_key": "genetic",
        "matched_class_key": "substitution_variant",
        "matched_class_path": [
          "genetic",
          "gene_modification_or_gain",
          "substitution_variant"
        ],
        "matched_definition": "Base or amino-acid substitution (for example SNV, point mutation, engineered missense).",
        "confidence": "high",
        "evidence": [
          "C8161.9 cells with endogenous TAO3 replacement by shRNA-TAO3 and wild-type TAO3 (shRNA-resistant, SR) or kinase-dead TAO3 (shRNA-resistant, KR)",
          "kinase-dead (via mutation of lysine 53 in the ATP binding site of the catalytic domain) TAO3"
        ]
      }
    ],
    "attributes": [
      {
        "relation_key": "has_treatment_agent",
        "agent": "wild-type TAO3 (SR) vs kinase-dead TAO3 (KR)",
        "dose_or_concentration": null,
        "duration": null,
        "route_or_context": "endogenous TAO3 replacement by shRNA-TAO3",
        "evidence": [
          "C8161.9 cells with endogenous TAO3 replacement by shRNA-TAO3 and wild-type TAO3 (shRNA-resistant, SR) or kinase-dead TAO3 (shRNA-resistant, KR)"
        ]
      }
    ],
    "source_sections": [
      "Ontology_TreatmentAndDesign_prompt"
    ]
  },
  "experimental_design": {
    "timepoints": [],
    "control_arms": [
      "wild-type TAO3 (SR)"
    ],
    "case_arms": [
      "kinase-dead TAO3 (KR)"
    ],
    "paired_design": false,
    "factorial_design": false,
    "replicate_hints": [
      "five 150 mm culture dishes"
    ],
    "multiplex_channel_hints": [
      "labeled with TMT reagents",
      "TMT6plex"
    ],
    "contrast_hints": [
      {
        "control_label": "wild-type TAO3 (SR)",
        "case_label": "kinase-dead TAO3 (KR)",
        "contrast_type": "pairwise",
        "evidence": [
          "identify and compare phosphopeptides in C8161.9 cells in which the endogenous TAO3 was replaced with either wild-type or kinase-inactive TAO3"
        ]
      }
    ],
    "source_sections": [
      "Ontology_TreatmentAndDesign_prompt"
    ]
  },
  "sample_source": {
    "human_system_present": "Yes",
    "organisms": [
      {
        "label": "Homo sapiens",
        "taxonomy_hint": "9606",
        "confidence": "high"
      }
    ],
    "cell_types": [],
    "cell_lines": [
      {
        "label": "C8161.9",
        "family": "melanoma",
        "ontology_curie": "CVCL_0196"
      }
    ],
    "noncellular_sources": [],
    "sample_scope": {
      "category": "subproteome",
      "label": "phosphoproteome",
      "curie": "PPA:0000195"
    },
    "linkage_hints": {
      "biosample_accessions": [],
      "sample_to_file_mapping_present": false
    },
    "source_sections": [
      "Ontology_SampleSourceAndScope_prompt"
    ]
  },
  "assay": {
    "acquisition_type": "DDA",
    "labeling_strategy": [
      "TMT"
    ],
    "quantification_strategy": [
      "TMT reporter ion peak intensities"
    ],
    "proteomics_mode": "PTM-enriched",
    "targets_and_enrichments": [
      {
        "ontology_label": "phosphoproteome enrichment",
        "ontology_curie": "PPA:0000292",
        "workflow_modifier_hint": "mod_phospho",
        "confidence": "high"
      }
    ],
    "assessor_support": null,
    "instrument_support": null,
    "source_sections": [
      "Ontology_AssayAndWorkflow_prompt"
    ]
  },
  "processing": {
    "reanalysis_compatibility": "Standard bottom-up reanalysis feasible",
    "workflow_hints": {
      "base_candidates_ranked": [
        {
          "base_workflow_id": "base_dda_isobaric",
          "confidence": 1.0,
          "reason": "The experiment explicitly uses TMT labeling (TMT6plex) and an Orbitrap Fusion Tribrid mass spectrometer for quantitative phosphoproteomics."
        }
      ],
      "modifier_candidates_ranked": [
        {
          "modifier_workflow_id": "phospho_enrichment",
          "confidence": 1.0,
          "reason": "Phosphopeptides were enriched using Titanosphere TiO2 5 um particles."
        }
      ],
      "trigger_keywords": [
        "TMT",
        "phosphoproteomics",
        "TiO2",
        "isobaric"
      ],
      "raw_or_file_name_triggers": []
    },
    "selection_hints": {
      "base_candidates_ranked": [
        {
          "base_workflow_id": "base_dda_isobaric",
          "confidence": 1.0,
          "reason": "The experiment explicitly uses TMT labeling (TMT6plex) and an Orbitrap Fusion Tribrid mass spectrometer for quantitative phosphoproteomics."
        }
      ],
      "modifier_candidates_ranked": [
        {
          "modifier_workflow_id": "phospho_enrichment",
          "confidence": 1.0,
          "reason": "Phosphopeptides were enriched using Titanosphere TiO2 5 um particles."
        }
      ],
      "trigger_keywords": [
        "TMT",
        "phosphoproteomics",
        "TiO2",
        "isobaric"
      ],
      "raw_or_file_name_triggers": []
    },
    "differential_hints": {
      "preferred_engine": "log2fc_site",
      "pairwise_strategy": "control_vs_case",
      "analyte_level": "site"
    },
    "source_sections": [
      "Ontology_ProcessingAndDifferential_prompt"
    ]
  },
  "stage4": {
    "workflow_id": null,
    "workflow_registry": null,
    "pipeline_workflow": null,
    "differential_summary": null,
    "pipeline_summary_available": false
  },
  "source_links": {
    "pride_project_url": "https://www.ebi.ac.uk/pride/archive/projects/PXD023867",
    "pmc_url": null,
    "pubmed_url": null
  },
  "provenance": {
    "stage3_metadata_available": true,
    "stage4_summary_available": false,
    "export_version": "2026-07-10",
    "public_evidence_policy": "links_only",
    "stage3_refreshed_at": "2026-07-13T06:31:01Z"
  }
}
